{
  "parent": "minecraft:recipes/root",
  "criteria": {
    "craft_iris_quartz_block": {
      "conditions": {
        "items": [
          {
            "items": "#c:storage_blocks/iris_quartz"
          }
        ]
      },
      "trigger": "minecraft:inventory_changed"
    },
    "has_the_recipe": {
      "conditions": {
        "recipe": "minium_me:iris_quartz_upgrade_smithing_template"
      },
      "trigger": "minecraft:recipe_unlocked"
    }
  },
  "requirements": [
    [
      "has_the_recipe",
      "craft_iris_quartz_block"
    ]
  ],
  "rewards": {
    "recipes": [
      "minium_me:iris_quartz_upgrade_smithing_template"
    ]
  }
}